dzcb/__init__.py
dzcb/__main__.py
dzcb/anytone.py
dzcb/contacts_trim.py
dzcb/exceptions.py
dzcb/farnsworth.py
dzcb/gb3gf.py
dzcb/k7abd.py
dzcb/log.py
dzcb/model.py
dzcb/munge.py
dzcb/pnwdigital.py
dzcb/recipe.py
dzcb/repeaterbook.py
dzcb/seattledmr.py
dzcb/tone.py
dzcb/util.py
dzcb/data/__init__.py
dzcb/data/repeaterbook_proximity_zones.csv
dzcb/data/scanlists.json
dzcb/data/dmrconfig/d868uv-default.conf
dzcb/data/dmrconfig/d878uv-default.conf
dzcb/data/dmrconfig/dmr6x2-default.conf
dzcb/data/dmrconfig/gd77-default.conf
dzcb/data/dmrconfig/md-uv380-default.conf
dzcb/data/dmrconfig/md380-default.conf
dzcb/data/dmrconfig/rd5r-default.conf
dzcb/data/farnsworth/__init__.py
dzcb/data/farnsworth/md-uv380.json
dzcb/data/farnsworth/md-uv390.json
dzcb/data/k7abd/Analog__Simplex.csv
dzcb/data/k7abd/Analog__Unlicensed.csv
dzcb/data/k7abd/Digital-Others__Simplex.csv
dzcb/data/k7abd/Talkgroups__Simplex.csv
dzcb/data/k7abd/__init__.py
dzcb/output/__init__.py
dzcb/output/dmrconfig.py
dzcb-0.3.10.dist-info/LICENSE
dzcb-0.3.10.dist-info/METADATA
dzcb-0.3.10.dist-info/WHEEL
dzcb-0.3.10.dist-info/top_level.txt
dzcb-0.3.10.dist-info/RECORD
