Metadata-Version: 2.1
Name: dzcb
Version: 0.3.10
Summary: DMR Zone Channel Builder
Home-page: https://github.com/mycodeplug/dzcb
Author: Masen Furer
Author-email: m_github@0x26.net
License: UNKNOWN
Platform: UNKNOWN
Classifier: Intended Audience :: Developers
Classifier: Development Status :: 3 - Alpha
Classifier: Operating System :: OS Independent
Classifier: License :: OSI Approved :: MIT License
Requires-Python: >=3.7,<4
Requires-Dist: appdirs ==1.4.4
Requires-Dist: attrs
Requires-Dist: geopy ==2.1.0
Requires-Dist: importlib-resources
Requires-Dist: requests ~=2.31
